{
    "baseline_test": {
        "mae": 22133.4356,
        "rmse": 30002.6098,
        "r2": -0.0001
    },
    "all_models": {
        "linear_regression": {
            "train": {
                "mae": 6536.4147,
                "rmse": 9748.4164,
                "r2": 0.8977
            },
            "test": {
                "mae": 6384.896,
                "rmse": 9482.0241,
                "r2": 0.9001
            },
            "overfit_gap_r2": -0.0024
        },
        "ridge": {
            "train": {
                "mae": 6535.6725,
                "rmse": 9748.4406,
                "r2": 0.8977
            },
            "test": {
                "mae": 6384.3456,
                "rmse": 9482.0758,
                "r2": 0.9001
            },
            "overfit_gap_r2": -0.0024
        },
        "random_forest": {
            "train": {
                "mae": 3011.9426,
                "rmse": 4279.6549,
                "r2": 0.9803
            },
            "test": {
                "mae": 3180.6324,
                "rmse": 4578.5124,
                "r2": 0.9767
            },
            "overfit_gap_r2": 0.0036
        },
        "gradient_boosting": {
            "train": {
                "mae": 3228.3759,
                "rmse": 4758.9815,
                "r2": 0.9756
            },
            "test": {
                "mae": 3188.0676,
                "rmse": 4648.4174,
                "r2": 0.976
            },
            "overfit_gap_r2": -0.0004
        }
    },
    "selected_model_name": "random_forest",
    "selected_model_train": {
        "mae": 3011.9426,
        "rmse": 4279.6549,
        "r2": 0.9803
    },
    "selected_model_test": {
        "mae": 3180.6324,
        "rmse": 4578.5124,
        "r2": 0.9767
    },
    "selected_model_overfit_gap_r2": 0.0036,
    "target_mean_train": 45494.9511,
    "n_rows": 50000,
    "n_train": 40000,
    "n_test": 10000,
    "data_path": "data/synthetic_healthcare_50k.csv"
}